[
  {
    "userId": 1234,
    "scores": [
      {
        "timestamp": "6/29/2022",
        "sleep": 1,
        "fatigue": 2,
        "stress": 3,
        "soreness": 4,
        "motivation": 5,
        "total": 15
      },
      {
        "timestamp": "6/29/2022, 10:14:13 PM",
        "sleep": 5,
        "fatigue": 5,
        "stress": 5,
        "soreness": 5,
        "motivation": 5,
        "total": 25
      },
      {
        "timestamp": "6/29/2022, 10:14:37 PM",
        "sleep": 2,
        "fatigue": 1,
        "stress": 2,
        "soreness": 1,
        "motivation": 2,
        "total": 8
      },
      {
        "timestamp": "6/29/2022, 10:14:13 PM",
        "sleep": 1,
        "fatigue": 2,
        "stress": 3,
        "soreness": 4,
        "motivation": 5,
        "total": 10
      },
      {
        "timestamp": "6/29/2022, 10:27:58 PM",
        "sleep": 0,
        "fatigue": 0,
        "stress": 0,
        "soreness": 0,
        "motivation": 0,
        "total": 0
      },
      {
        "timestamp": "6/29/2022, 10:31:54 PM",
        "sleep": 0,
        "fatigue": 0,
        "stress": 0,
        "soreness": 0,
        "motivation": 0,
        "total": 0
      },
      {
        "timestamp": "6/29/2022, 10:42:49 PM",
        "sleep": 0,
        "fatigue": 0,
        "stress": 0,
        "soreness": 0,
        "motivation": 0,
        "total": 0
      },
      {
        "timestamp": "6/30/2022, 9:49:09 AM",
        "sleep": 0,
        "fatigue": 0,
        "stress": 0,
        "soreness": 0,
        "motivation": 0,
        "total": 0
      }
    ]
  }
]
